ucnn/__init__.py
ucnn/cnn_model.py
ucnn/input_image.py
ucnn/predict.py
ucnn/record.py
ucnn/static.py
ucnn/train.py
ucnn-0.1.7.data/scripts/ucnn
ucnn-0.1.7.dist-info/DESCRIPTION.rst
ucnn-0.1.7.dist-info/METADATA
ucnn-0.1.7.dist-info/RECORD
ucnn-0.1.7.dist-info/WHEEL
ucnn-0.1.7.dist-info/metadata.json
ucnn-0.1.7.dist-info/top_level.txt
