Metadata-Version: 2.0
Name: ucnn
Version: 0.1.7
Summary: Universal CNN Training & Predicting For Fixed-Length Label Captcha.
Home-page: https://github.com/Jiramew/universal_cnn
Author: Jiramew
Author-email: hanbingflying@sina.com
License: BSD License
Platform: all
Classifier: Development Status :: 3 - Alpha
Classifier: License :: OSI Approved :: BSD License
Classifier: Programming Language :: Python
Classifier: Programming Language :: Python :: 3
Classifier: Programming Language :: Python :: 3.6
Classifier: Topic :: Software Development :: Libraries
Requires-Dist: pillow (>=4.2.1)
Requires-Dist: tensorflow (>=1.4.0)
